wheel_filename/__init__.py
wheel_filename/__main__.py
wheel_filename/py.typed
wheel_filename-2.1.0.dist-info/METADATA
wheel_filename-2.1.0.dist-info/WHEEL
wheel_filename-2.1.0.dist-info/entry_points.txt
wheel_filename-2.1.0.dist-info/licenses/LICENSE
wheel_filename-2.1.0.dist-info/RECORD
