Metadata-Version: 2.4
Name: wheel-filename
Version: 2.1.0
Summary: Parse wheel filenames
Project-URL: Source Code, https://github.com/wheelodex/wheel-filename
Project-URL: Bug Tracker, https://github.com/wheelodex/wheel-filename/issues
Author-email: John Thorvald Wodder II <wheel-filename@varonathe.org>
License-Expression: MIT
License-File: LICENSE
Keywords: filename,pep427,wheel
Classifier: Development Status :: 5 - Production/Stable
Classifier: Programming Language :: Python :: 3
Classifier: Programming Language :: Python :: 3 :: Only
Classifier: Programming Language :: Python :: 3.10
Classifier: Programming Language :: Python :: 3.11
Classifier: Programming Language :: Python :: 3.12
Classifier: Programming Language :: Python :: 3.13
Classifier: Programming Language :: Python :: 3.14
Classifier: Programming Language :: Python :: Implementation :: CPython
Classifier: Programming Language :: Python :: Implementation :: PyPy
Classifier: Topic :: System :: Software Distribution
Classifier: Typing :: Typed
Requires-Python: >=3.10
